setup.py
django_puppy_cache.egg-info/PKG-INFO
django_puppy_cache.egg-info/SOURCES.txt
django_puppy_cache.egg-info/dependency_links.txt
django_puppy_cache.egg-info/not-zip-safe
django_puppy_cache.egg-info/top_level.txt
puppy/__init__.py
puppy/memcached.py
puppy/redis.py