Metadata-Version: 1.1
Name: django-puppy-cache
Version: 1.3.0
Summary: Django cache backend that helps prevent dog-piling.
Home-page: http://github.com/funkybob/puppy
Author: Curtis Maloney
Author-email: curtis@commoncode.com.au
License: UNKNOWN
Keywords: django,redis,cache,memcached
Platform: UNKNOWN
Classifier: Environment :: Web Environment
Classifier: Framework :: Django
Classifier: License :: OSI Approved :: BSD License
Classifier: Operating System :: OS Independent
Classifier: Programming Language :: Python
Requires: Django (>=1.5)
